flask_weasyprint/__init__.py
flask_weasyprint/test_app.py
flask_weasyprint/tests.py
Flask_WeasyPrint-0.6.dist-info/LICENSE
Flask_WeasyPrint-0.6.dist-info/METADATA
Flask_WeasyPrint-0.6.dist-info/WHEEL
Flask_WeasyPrint-0.6.dist-info/top_level.txt
Flask_WeasyPrint-0.6.dist-info/RECORD
