Metadata-Version: 1.1
Name: Flask-WeasyPrint
Version: 0.6
Summary: Make PDF in your Flask app with WeasyPrint.
Home-page: https://github.com/SimonSapin/Flask-WeasyPrint
Author: Simon Sapin
Author-email: simon.sapin@exyr.org
License: BSD
Platform: any
Classifier: Environment :: Web Environment
Classifier: Intended Audience :: Developers
Classifier: License :: OSI Approved :: BSD License
Classifier: Operating System :: OS Independent
Classifier: Programming Language :: Python
Classifier: Topic :: Internet :: WWW/HTTP :: Dynamic Content
Classifier: Topic :: Software Development :: Libraries :: Python Modules
